example_pkg/__init__.py
example_pkg/calculation/__init__.py
example_pkg/calculation/simple.py
yangyuan_pkg_learn-0.0.4.dist-info/LICENSE
yangyuan_pkg_learn-0.0.4.dist-info/METADATA
yangyuan_pkg_learn-0.0.4.dist-info/WHEEL
yangyuan_pkg_learn-0.0.4.dist-info/top_level.txt
yangyuan_pkg_learn-0.0.4.dist-info/RECORD
